simple_botmaker/__init__.py
simple_botmaker/globals.py
simple_botmaker/high_level_functions.py
simple_botmaker/low_level_functions.py
simple_botmaker/custom_interpreter/__init__.py
simple_botmaker/custom_interpreter/definitions.py
simple_botmaker/custom_interpreter/interpreter.py
simple_botmaker-0.0.2.dist-info/licenses/LICENSE
simple_botmaker-0.0.2.dist-info/METADATA
simple_botmaker-0.0.2.dist-info/WHEEL
simple_botmaker-0.0.2.dist-info/entry_points.txt
simple_botmaker-0.0.2.dist-info/top_level.txt
simple_botmaker-0.0.2.dist-info/RECORD
