Metadata-Version: 2.4
Name: simple-botmaker
Version: 0.0.2
Summary: A package that simplifies the creation of bots that react to the screen in real time
Home-page: https://github.com/yourusername/simple-botmaker
Author: Jayden Clarke
Author-email: 
License: Creative Commons Attribution-NonCommercial 4.0 International (CC BY-NC 4.0)
Project-URL: Homepage, https://github.com/BARKEM-JC/simple-botmaker
Keywords: automation,bot,screen-capture,ocr,image-recognition,windows
Platform: win32
Classifier: Development Status :: 4 - Beta
Classifier: Intended Audience :: Developers
Classifier: License :: OSI Approved :: MIT License
Classifier: Operating System :: Microsoft :: Windows
Classifier: Programming Language :: Python :: 3
Classifier: Programming Language :: Python :: 3.7
Classifier: Programming Language :: Python :: 3.8
Classifier: Programming Language :: Python :: 3.9
Classifier: Programming Language :: Python :: 3.10
Classifier: Programming Language :: Python :: 3.11
Classifier: Programming Language :: Python :: 3.12
Classifier: Topic :: Software Development :: Libraries :: Python Modules
Classifier: Topic :: Games/Entertainment
Classifier: Topic :: Multimedia :: Graphics :: Capture :: Screen Capture
Classifier: Topic :: Scientific/Engineering :: Image Recognition
Requires-Python: >=3.7
License-File: LICENSE
Requires-Dist: opencv-python~=4.12.0.88
Requires-Dist: numpy~=2.2.6
Requires-Dist: PyWinCtl~=0.4.1
Requires-Dist: mss~=10.0.0
Requires-Dist: PyAutoGUI~=0.9.54
Requires-Dist: Pillow>=8.0.0
Provides-Extra: dev
Requires-Dist: pytest>=6.0; extra == "dev"
Requires-Dist: pytest-cov; extra == "dev"
Requires-Dist: black; extra == "dev"
Requires-Dist: flake8; extra == "dev"
Requires-Dist: mypy; extra == "dev"
Dynamic: home-page
Dynamic: license-file
Dynamic: platform
Dynamic: requires-python
